checks/__init__.py
checks/__main__.py
checks/cli.py
checks/commands.py
checks/exceptions.py
checks/models.py
checks/parser.py
checks/utils.py
checks/db/__init__.py
checks/db/json_database.py
checks_cli-1.1.0.dist-info/LICENSE
checks_cli-1.1.0.dist-info/METADATA
checks_cli-1.1.0.dist-info/WHEEL
checks_cli-1.1.0.dist-info/entry_points.txt
checks_cli-1.1.0.dist-info/top_level.txt
checks_cli-1.1.0.dist-info/RECORD
