Metadata-Version: 2.1
Name: checks-cli
Version: 1.1.0
Summary: Command-line tool to manage tasks list.
Home-page: https://github.com/anas-shakeel/checks
Author: Anas Shakeel
License: MIT
Keywords: todo,task,task-manager,tasklist,todo-list,cli,command-line,productivity,organizer
Classifier: Programming Language :: Python :: 3
Classifier: License :: OSI Approved :: MIT License
Classifier: Operating System :: OS Independent
License-File: LICENSE
Requires-Dist: pinsy
Requires-Dist: tabulate
